africanwordnet/__init__.py
africanwordnet/nltk.py
africanwordnet-0.0.1.dist-info/LICENSE
africanwordnet-0.0.1.dist-info/METADATA
africanwordnet-0.0.1.dist-info/WHEEL
africanwordnet-0.0.1.dist-info/top_level.txt
africanwordnet-0.0.1.dist-info/RECORD
